ai_governance/__init__.py
ai_governance-0.0.3.dist-info/METADATA
ai_governance-0.0.3.dist-info/WHEEL
ai_governance-0.0.3.dist-info/RECORD
